Struts2KuangjiaRumenjiaochengCYuyanBianchengWangFix1/README.md
Struts2KuangjiaRumenjiaochengCYuyanBianchengWangFix1/__init__.py
Struts2KuangjiaRumenjiaochengCYuyanBianchengWangFix1/__main__.py
Struts2KuangjiaRumenjiaochengCYuyanBianchengWangFix1/file.epub
Struts2KuangjiaRumenjiaochengCYuyanBianchengWangFix1/index.html
Struts2KuangjiaRumenjiaochengCYuyanBianchengWangFix1/css/__init__.py
Struts2KuangjiaRumenjiaochengCYuyanBianchengWangFix1/css/annotations.css
Struts2KuangjiaRumenjiaochengCYuyanBianchengWangFix1/css/main.css
Struts2KuangjiaRumenjiaochengCYuyanBianchengWangFix1/css/normalize.css
Struts2KuangjiaRumenjiaochengCYuyanBianchengWangFix1/css/popup.css
Struts2KuangjiaRumenjiaochengCYuyanBianchengWangFix1/font/__init__.py
Struts2KuangjiaRumenjiaochengCYuyanBianchengWangFix1/font/fontello.eot
Struts2KuangjiaRumenjiaochengCYuyanBianchengWangFix1/font/fontello.svg
Struts2KuangjiaRumenjiaochengCYuyanBianchengWangFix1/font/fontello.ttf
Struts2KuangjiaRumenjiaochengCYuyanBianchengWangFix1/font/fontello.woff
Struts2KuangjiaRumenjiaochengCYuyanBianchengWangFix1/img/__init__.py
Struts2KuangjiaRumenjiaochengCYuyanBianchengWangFix1/img/annotator-glyph-sprite.png
Struts2KuangjiaRumenjiaochengCYuyanBianchengWangFix1/img/annotator-icon-sprite.png
Struts2KuangjiaRumenjiaochengCYuyanBianchengWangFix1/img/apple-touch-icon.png
Struts2KuangjiaRumenjiaochengCYuyanBianchengWangFix1/img/cancelfullscreen.png
Struts2KuangjiaRumenjiaochengCYuyanBianchengWangFix1/img/close.png
Struts2KuangjiaRumenjiaochengCYuyanBianchengWangFix1/img/fullscreen.png
Struts2KuangjiaRumenjiaochengCYuyanBianchengWangFix1/img/loader.gif
Struts2KuangjiaRumenjiaochengCYuyanBianchengWangFix1/img/menu-icon.png
Struts2KuangjiaRumenjiaochengCYuyanBianchengWangFix1/img/save.png
Struts2KuangjiaRumenjiaochengCYuyanBianchengWangFix1/img/saved.png
Struts2KuangjiaRumenjiaochengCYuyanBianchengWangFix1/img/settings-s.png
Struts2KuangjiaRumenjiaochengCYuyanBianchengWangFix1/img/settings.png
struts2_kuangjia_rumenjiaocheng_c_yuyan_biancheng_wang_fix1-2025.3.24.0.dist-info/METADATA
struts2_kuangjia_rumenjiaocheng_c_yuyan_biancheng_wang_fix1-2025.3.24.0.dist-info/WHEEL
struts2_kuangjia_rumenjiaocheng_c_yuyan_biancheng_wang_fix1-2025.3.24.0.dist-info/entry_points.txt
struts2_kuangjia_rumenjiaocheng_c_yuyan_biancheng_wang_fix1-2025.3.24.0.dist-info/top_level.txt
struts2_kuangjia_rumenjiaocheng_c_yuyan_biancheng_wang_fix1-2025.3.24.0.dist-info/RECORD
